invenio_oauth2server/__init__.py
invenio_oauth2server/admin.py
invenio_oauth2server/cli.py
invenio_oauth2server/config.py
invenio_oauth2server/decorators.py
invenio_oauth2server/errors.py
invenio_oauth2server/ext.py
invenio_oauth2server/forms.py
invenio_oauth2server/models.py
invenio_oauth2server/provider.py
invenio_oauth2server/proxies.py
invenio_oauth2server/scopes.py
invenio_oauth2server/utils.py
invenio_oauth2server/validators.py
invenio_oauth2server/alembic/12a88921ada2_create_oauth2server_tables.py
invenio_oauth2server/alembic/4e57407b8e4a_add_on_delete_cascade.py
invenio_oauth2server/alembic/aa546f2a8d2f_create_oauth2server_branch.py
invenio_oauth2server/templates/invenio_oauth2server/authorize.html
invenio_oauth2server/templates/invenio_oauth2server/base.html
invenio_oauth2server/templates/invenio_oauth2server/errors.html
invenio_oauth2server/templates/invenio_oauth2server/settings/_macros.html
invenio_oauth2server/templates/invenio_oauth2server/settings/base.html
invenio_oauth2server/templates/invenio_oauth2server/settings/client_new.html
invenio_oauth2server/templates/invenio_oauth2server/settings/client_view.html
invenio_oauth2server/templates/invenio_oauth2server/settings/helpers.html
invenio_oauth2server/templates/invenio_oauth2server/settings/index.html
invenio_oauth2server/templates/invenio_oauth2server/settings/token_new.html
invenio_oauth2server/templates/invenio_oauth2server/settings/token_permission_view.html
invenio_oauth2server/templates/invenio_oauth2server/settings/token_view.html
invenio_oauth2server/templates/semantic-ui/invenio_oauth2server/authorize.html
invenio_oauth2server/templates/semantic-ui/invenio_oauth2server/base.html
invenio_oauth2server/templates/semantic-ui/invenio_oauth2server/errors.html
invenio_oauth2server/templates/semantic-ui/invenio_oauth2server/settings/_macros.html
invenio_oauth2server/templates/semantic-ui/invenio_oauth2server/settings/base.html
invenio_oauth2server-3.3.2.dist-info/licenses/AUTHORS.rst
invenio_oauth2server-3.3.2.dist-info/licenses/LICENSE
invenio_oauth2server-3.3.2.dist-info/METADATA
invenio_oauth2server-3.3.2.dist-info/WHEEL
invenio_oauth2server-3.3.2.dist-info/entry_points.txt
invenio_oauth2server-3.3.2.dist-info/top_level.txt
invenio_oauth2server-3.3.2.dist-info/RECORD
