Metadata-Version: 2.4
Name: invenio-oauth2server
Version: 3.3.2
Summary: "Invenio module that implements OAuth 2 server."
Home-page: https://github.com/inveniosoftware/invenio-oauth2server
Author: CERN
Author-email: info@inveniosoftware.org
License: MIT
Keywords: invenio OAuth2 server
Platform: any
Classifier: Development Status :: 5 - Production/Stable
Requires-Python: >=3.7
License-File: LICENSE
License-File: AUTHORS.rst
Requires-Dist: cachelib>=0.1
Requires-Dist: Flask-OAuthlib-Invenio>=1.0.0
Requires-Dist: Flask-WTF>=0.14.3
Requires-Dist: future>=0.16.0
Requires-Dist: invenio-accounts<7.0.0,>=6.0.0
Requires-Dist: invenio-base<3.0.0,>=2.3.0
Requires-Dist: invenio-i18n<4.0.0,>=3.0.0
Requires-Dist: invenio-theme<5.0.0,>=4.0.0
Requires-Dist: pyjwt>=1.5.0
Requires-Dist: requests-oauthlib>=1.1.0
Requires-Dist: WTForms-Alchemy>=0.15.0
Requires-Dist: WTForms>=3.0.0
Requires-Dist: importlib_metadata>=4.4
Provides-Extra: tests
Requires-Dist: pytest-black-ng>=0.4.0; extra == "tests"
Requires-Dist: pytest-invenio<4.0.0,>=3.0.0; extra == "tests"
Requires-Dist: invenio-admin>=1.2.1; extra == "tests"
Requires-Dist: sphinx>=4.5; extra == "tests"
Requires-Dist: redis>=2.10.5; extra == "tests"
Requires-Dist: invenio-db[mysql,postgresql,versioning]<3.0.0,>=2.0.0; extra == "tests"
Provides-Extra: admin
Provides-Extra: docs
Provides-Extra: redis
Provides-Extra: mysql
Provides-Extra: postgresql
Provides-Extra: sqlite
Dynamic: license-file
